s_test/__init__.py
s_test/__version__.py
s_test/a.py
s_test/b.py
s_test/c.py
s_test-0.0.3.dist-info/METADATA
s_test-0.0.3.dist-info/RECORD
s_test-0.0.3.dist-info/WHEEL
s_test-0.0.3.dist-info/top_level.txt
s_test-0.0.3.dist-info/zip-safe
